src/uart.v
`timescale 1ns/1ps
module uart_rx #(parameter integer DIV = 5208) (
    input wire clk, rst_p, rx,
    output reg [7:0] data,
    output reg valid,
    output reg framing_error
);

    (* ASYNC_REG="TRUE" *) reg [1:0] sync;
    reg [1:0] state;
    integer timer;
    reg [2:0] bitno;
    reg [7:0] shift;

    always @(posedge clk) begin
        if (rst_p) begin
            sync <= 3; state <= 0;
            timer <= 0; bitno <= 0; shift <= 0;
            data <= 0; valid <= 0;
            framing_error <= 0;
        end else begin
            sync <= {sync[0], rx}; valid <= 0; framing_error <= 0;
            case(state)
                0: if(!sync[1]) begin timer <= DIV/2-1; state <= 1; end
                1: if(timer != 0) timer <= timer-1;
                   else if(sync[1]) state <= 0;
                   else begin timer <= DIV-1; bitno <= 0; state <= 2; end
                2: if(timer != 0) timer <= timer-1;
                   else begin
                       shift[bitno] <= sync[1];
                       timer <= DIV-1;
                       if(bitno == 7) state <= 3;
                       else bitno <= bitno+1'b1;
                   end
                3: if(timer != 0) timer <= timer-1;
                   else begin
                       if(sync[1]) begin data <= shift; valid <= 1; end
                       else framing_error <= 1;
                       state <= 0;
                   end
            endcase
        end
    end
endmodule

module uart_tx #(parameter integer DIV = 5208) (
    input wire clk, rst_p, valid,
    input wire [7:0] data,
    output wire ready,
    output wire tx
);

    reg [9:0] shift;
    reg [3:0] remaining;
    integer timer;

    assign ready = (remaining == 0);
    assign tx = ready ? 1'b1 : shift[0];

    always @(posedge clk) begin
        if(rst_p) begin shift <= 10'h3ff; remaining <= 0; timer <= 0; end
        else if (ready) begin
            if(valid) begin shift <= {1'b1, data, 1'b0}; remaining <= 10; timer <= DIV-1; end
        end else if(timer != 0) timer <= timer-1;
        else begin timer <= DIV-1; shift <= {1'b1, shift[9:1]}; remaining <= remaining-1'b1; end
    end
endmodule

src/lab3_uart_echo.v
`timescale 1ns/1ps
module lab3_uart_echo #(
    parameter integer CLK_HZ = 50_000_000,
    parameter integer BAUD = 9_600
)(
    input wire clk_50mhz,
    input wire rst_p,
    input wire uart_rxd,
    output wire uart_txd,
    output wire [7:0] led
);

    localparam integer DIV = (CLK_HZ + BAUD/2)/BAUD;
    wire [7:0] rx_data;
    wire rx_valid;
    wire rx_framing_error;
    wire tx_ready;
    reg tx_valid;
    reg [7:0] tx_data;
    reg [7:0] last_data;

    uart_rx #(.DIV(DIV)) u_rx(
        .clk(clk_50mhz), .rst_p(rst_p), .rx(uart_rxd), .data(rx_data),
        .valid(rx_valid), .framing_error(rx_framing_error));

    uart_tx #(.DIV(DIV)) u_tx(
        .clk(clk_50mhz), .rst_p(rst_p), .valid(tx_valid), .data(tx_data),
        .ready(tx_ready), .tx(uart_txd));

    always @(posedge clk_50mhz or posedge rst_p) begin
        if (rst_p) begin
            tx_valid <= 0; tx_data <= 0; last_data <= 0;
        end else begin
            tx_valid <= 0;
            if (rx_valid) begin
                last_data <= rx_data;
                if (tx_ready) begin
                    tx_data <= rx_data;
                    tx_valid <= 1;
                end
            end
        end
    end

    assign led = last_data;
endmodule

sim/tb_uart_echo.sv
`timescale 1ns/1ps
module tb_uart_echo;
    localparam integer DIV = 8;
    reg clk_50mhz = 0, rst_p = 1, uart_rxd = 1;
    wire uart_txd;
    wire [7:0] led;
    reg [7:0] observed;
    integer checks = 0, i;

    always #10 clk_50mhz = ~clk_50mhz;

    lab3_uart_echo #(.CLK_HZ(800), .BAUD(200)) dut (
        .clk_50mhz(clk_50mhz), .rst_p(rst_p), .uart_rxd(uart_rxd), .uart_txd(uart_txd), .led(led)
    );

    task send_byte (input [7:0] value);
        begin
            uart_rxd = 0; repeat (DIV) @(posedge clk_50mhz);
            for(i = 0; i < 8; i = i + 1) begin uart_rxd = value[i]; repeat(DIV) @(posedge clk_50mhz); end
            uart_rxd = 1; repeat (DIV) @(posedge clk_50mhz);
        end
    endtask

    task receive_byte(input [7:0] expected);
        begin
            observed = 0; @(negedge uart_txd); repeat(DIV + DIV/2) @(posedge clk_50mhz);
            for(i = 0; i < 8; i = i + 1) begin observed[i] = uart_txd; repeat(DIV) @(posedge clk_50mhz); end
            if(observed !== expected) $fatal(1, "echo=%h expected=%h", observed, expected);
            if(led !== expected) $fatal(1, "led=%h expected=%h", led, expected);
            checks = checks + 1; repeat(DIV) @(posedge clk_50mhz);
        end
    endtask

    initial begin
        $dumpfile("wave.vcd"); $dumpvars(0, tb_uart_echo);
        repeat(4) @(posedge clk_50mhz); rst_p = 0;
        fork send_byte(8'h41); receive_byte(8'h41); join
        fork send_byte(8'h5a); receive_byte(8'h5a); join
        fork send_byte(8'h0a); receive_byte(8'h0a); join
        if(dut.rx_framing_error) $fatal(1, "unexpected framing error");
        $display("LAB3_UART_ECHO_PASS checks=%0d", checks); $finish;
    end

    initial begin #50000; $fatal(1, "timeout"); end
endmodule

evidence/07/vscode/wave.vcd
$date
	Tue Sep 22 14:46:21 2026
$end
$version
	Icarus Verilog
$end
$timescale
	1ps
$end
$scope module tb_uart_echo $end
$var wire 1 ! uart_txd $end
$var wire 8 " led [7:0] $end
$var parameter 32 # DIV $end
$var reg 1 $ clk_50mhz $end
$var reg 8 % observed [7:0] $end
$var reg 1 & rst_p $end
$var reg 1 ' uart_rxd $end
$var integer 32 ( checks [31:0] $end
$var integer 32 ) i [31:0] $end
$scope module dut $end
$var wire 1 $ clk_50mhz $end
$var wire 8 * led [7:0] $end
$var wire 1 & rst_p $end
$var wire 1 ' uart_rxd $end
$var wire 1 ! uart_txd $end
$var wire 1 + tx_ready $end
$var wire 1 , rx_valid $end
$var wire 1 - rx_framing_error $end
$var wire 8 . rx_data [7:0] $end
$var parameter 32 / BAUD $end
$var parameter 32 0 CLK_HZ $end
$var parameter 32 1 DIV $end
$var reg 8 2 last_data [7:0] $end
$var reg 8 3 tx_data [7:0] $end
$var reg 1 4 tx_valid $end
$scope module u_rx $end
$var wire 1 $ clk $end
$var wire 1 & rst_p $end
$var wire 1 ' rx $end
$var parameter 32 5 DIV $end
$var reg 3 6 bitno [2:0] $end
$var reg 8 7 data [7:0] $end
$var reg 1 - framing_error $end
$var reg 8 8 shift [7:0] $end
$var reg 2 9 state [1:0] $end
$var reg 2 : sync [1:0] $end
$var reg 1 , valid $end
$var integer 32 ; timer [31:0] $end
$upscope $end
$scope module u_tx $end
$var wire 1 $ clk $end
$var wire 8 < data [7:0] $end
$var wire 1 & rst_p $end
$var wire 1 4 valid $end
$var wire 1 ! tx $end
$var wire 1 + ready $end
$var parameter 32 = DIV $end
$var reg 4 > remaining [3:0] $end
$var reg 10 ? shift [9:0] $end
$var integer 32 @ timer [31:0] $end
$upscope $end
$upscope $end
$scope task receive_byte $end
$var reg 8 A expected [7:0] $end
$upscope $end
$scope task send_byte $end
$var reg 8 B value [7:0] $end
$upscope $end
$upscope $end
$enddefinitions $end
$comment Show the parameter values. $end
$dumpall
b1000 =
b1000 5
b1000 1
b1100100000 0
b1100100 /
b1000 #
$end
#0
$dumpvars
bx B
bx A
bx @
bx ?
bx >
bx <
bx ;
bx :
bx 9
bx 8
bx 7
bx 6
x4
bx 3
bx 2
bx .
x-
x,
x+
bx *
bx )
b0 (
1'
1&
bx %
0$
bx "
x!
$end
#10000
1!
1+
0-
0,
b0 .
b0 7
b0 8
b0 6
b0 ;
b0 9
b11 :
b0 @
b0 >
b1111111111 ?
b0 "
b0 *
b0 2
b0 3
b0 <
04
1$
#20000
0$
#30000
1$
#40000
0$
#50000
1$
#60000
0$
#70000
0'
b1000001 B
b0 %
b1000001 A
0&
1$
#80000
0$
#90000
b10 :
1$
#100000
0$
#110000
b0 :
1$
#120000
0$
#130000
b1 9
b11 ;
1$
#140000
0$
#150000
b10 ;
1$
#160000
0$
#170000
b1 ;
1$
#180000
0$
#190000
b0 ;
1$
#200000
0$
#210000
b10 9
b111 ;
1$
#220000
0$
#230000
b110 ;
1'
b0 )
1$
#240000
0$
#250000
b101 ;
b1 :
1$
#260000
0$
#270000
b100 ;
b11 :
1$
#280000
0$
#290000
b11 ;
1$
#300000
0$
#310000
b10 ;
1$
#320000
0$
#330000
b1 ;
1$
#340000
0$
#350000
b0 ;
1$
#360000
0$
#370000
b1 6
b111 ;
b1 8
1$
#380000
0$
#390000
b110 ;
0'
b1 )
1$
#400000
0$
#410000
b101 ;
b10 :
1$
#420000
0$
#430000
b100 ;
b0 :
1$
#440000
0$
#450000
b11 ;
1$
#460000
0$
#470000
b10 ;
1$
#480000
0$
#490000
b1 ;
1$
#500000
0$
#510000
b0 ;
1$
#520000
0$
#530000
b10 6
b111 ;
1$
#540000
0$
#550000
b110 ;
b10 )
1$
#560000
0$
#570000
b101 ;
1$
#580000
0$
#590000
b100 ;
1$
#600000
0$
#610000
b11 ;
1$
#620000
0$
#630000
b10 ;
1$
#640000
0$
#650000
b1 ;
1$
#660000
0$
#670000
b0 ;
1$
#680000
0$
#690000
b11 6
b111 ;
1$
#700000
0$
#710000
b110 ;
b11 )
1$
#720000
0$
#730000
b101 ;
1$
#740000
0$
#750000
b100 ;
1$
#760000
0$
#770000
b11 ;
1$
#780000
0$
#790000
b10 ;
1$
#800000
0$
#810000
b1 ;
1$
#820000
0$
#830000
b0 ;
1$
#840000
0$
#850000
b100 6
b111 ;
1$
#860000
0$
#870000
b110 ;
b100 )
1$
#880000
0$
#890000
b101 ;
1$
#900000
0$
#910000
b100 ;
1$
#920000
0$
#930000
b11 ;
1$
#940000
0$
#950000
b10 ;
1$
#960000
0$
#970000
b1 ;
1$
#980000
0$
#990000
b0 ;
1$
#1000000
0$
#1010000
b101 6
b111 ;
1$
#1020000
0$
#1030000
b110 ;
b101 )
1$
#1040000
0$
#1050000
b101 ;
1$
#1060000
0$
#1070000
b100 ;
1$
#1080000
0$
#1090000
b11 ;
1$
#1100000
0$
#1110000
b10 ;
1$
#1120000
0$
#1130000
b1 ;
1$
#1140000
0$
#1150000
b0 ;
1$
#1160000
0$
#1170000
b110 6
b111 ;
1$
#1180000
0$
#1190000
b110 ;
1'
b110 )
1$
#1200000
0$
#1210000
b101 ;
b1 :
1$
#1220000
0$
#1230000
b100 ;
b11 :
1$
#1240000
0$
#1250000
b11 ;
1$
#1260000
0$
#1270000
b10 ;
1$
#1280000
0$
#1290000
b1 ;
1$
#1300000
0$
#1310000
b0 ;
1$
#1320000
0$
#1330000
b111 6
b111 ;
b1000001 8
1$
#1340000
0$
#1350000
b110 ;
0'
b111 )
1$
#1360000
0$
#1370000
b101 ;
b10 :
1$
#1380000
0$
#1390000
b100 ;
b0 :
1$
#1400000
0$
#1410000
b11 ;
1$
#1420000
0$
#1430000
b10 ;
1$
#1440000
0$
#1450000
b1 ;
1$
#1460000
0$
#1470000
b0 ;
1$
#1480000
0$
#1490000
b11 9
b111 ;
1$
#1500000
0$
#1510000
b110 ;
1'
b1000 )
1$
#1520000
0$
#1530000
b101 ;
b1 :
1$
#1540000
0$
#1550000
b100 ;
b11 :
1$
#1560000
0$
#1570000
b11 ;
1$
#1580000
0$
#1590000
b10 ;
1$
#1600000
0$
#1610000
b1 ;
1$
#1620000
0$
#1630000
b0 ;
1$
#1640000
0$
#1650000
b0 9
1,
b1000001 .
b1000001 7
1$
#1660000
0$
#1670000
0,
14
b1000001 3
b1000001 <
b1000001 "
b1000001 *
b1000001 2
1$
#1680000
0$
#1690000
0!
0+
b111 @
b1010 >
b1010000010 ?
04
1$
#1700000
0$
#1710000
b110 @
1$
#1720000
0$
#1730000
b101 @
1$
#1740000
0$
#1750000
b100 @
1$
#1760000
0$
#1770000
b11 @
1$
#1780000
0$
#1790000
b10 @
1$
#1800000
0$
#1810000
b1 @
1$
#1820000
0$
#1830000
b0 @
1$
#1840000
0$
#1850000
1!
b1001 >
b1101000001 ?
b111 @
1$
#1860000
0$
#1870000
b110 @
1$
#1880000
0$
#1890000
b101 @
1$
#1900000
0$
#1910000
b100 @
1$
#1920000
0$
#1930000
b11 @
b1 %
b0 )
1$
#1940000
0$
#1950000
b10 @
1$
#1960000
0$
#1970000
b1 @
1$
#1980000
0$
#1990000
b0 @
1$
#2000000
0$
#2010000
0!
b1000 >
b1110100000 ?
b111 @
1$
#2020000
0$
#2030000
b110 @
1$
#2040000
0$
#2050000
b101 @
1$
#2060000
0$
#2070000
b100 @
1$
#2080000
0$
#2090000
b11 @
b1 )
1$
#2100000
0$
#2110000
b10 @
1$
#2120000
0$
#2130000
b1 @
1$
#2140000
0$
#2150000
b0 @
1$
#2160000
0$
#2170000
b111 >
b1111010000 ?
b111 @
1$
#2180000
0$
#2190000
b110 @
1$
#2200000
0$
#2210000
b101 @
1$
#2220000
0$
#2230000
b100 @
1$
#2240000
0$
#2250000
b11 @
b10 )
1$
#2260000
0$
#2270000
b10 @
1$
#2280000
0$
#2290000
b1 @
1$
#2300000
0$
#2310000
b0 @
1$
#2320000
0$
#2330000
b110 >
b1111101000 ?
b111 @
1$
#2340000
0$
#2350000
b110 @
1$
#2360000
0$
#2370000
b101 @
1$
#2380000
0$
#2390000
b100 @
1$
#2400000
0$
#2410000
b11 @
b11 )
1$
#2420000
0$
#2430000
b10 @
1$
#2440000
0$
#2450000
b1 @
1$
#2460000
0$
#2470000
b0 @
1$
#2480000
0$
#2490000
b101 >
b1111110100 ?
b111 @
1$
#2500000
0$
#2510000
b110 @
1$
#2520000
0$
#2530000
b101 @
1$
#2540000
0$
#2550000
b100 @
1$
#2560000
0$
#2570000
b11 @
b100 )
1$
#2580000
0$
#2590000
b10 @
1$
#2600000
0$
#2610000
b1 @
1$
#2620000
0$
#2630000
b0 @
1$
#2640000
0$
#2650000
b100 >
b1111111010 ?
b111 @
1$
#2660000
0$
#2670000
b110 @
1$
#2680000
0$
#2690000
b101 @
1$
#2700000
0$
#2710000
b100 @
1$
#2720000
0$
#2730000
b11 @
b101 )
1$
#2740000
0$
#2750000
b10 @
1$
#2760000
0$
#2770000
b1 @
1$
#2780000
0$
#2790000
b0 @
1$
#2800000
0$
#2810000
1!
b11 >
b1111111101 ?
b111 @
1$
#2820000
0$
#2830000
b110 @
1$
#2840000
0$
#2850000
b101 @
1$
#2860000
0$
#2870000
b100 @
1$
#2880000
0$
#2890000
b11 @
b1000001 %
b110 )
1$
#2900000
0$
#2910000
b10 @
1$
#2920000
0$
#2930000
b1 @
1$
#2940000
0$
#2950000
b0 @
1$
#2960000
0$
#2970000
0!
b10 >
b1111111110 ?
b111 @
1$
#2980000
0$
#2990000
b110 @
1$
#3000000
0$
#3010000
b101 @
1$
#3020000
0$
#3030000
b100 @
1$
#3040000
0$
#3050000
b11 @
b111 )
1$
#3060000
0$
#3070000
b10 @
1$
#3080000
0$
#3090000
b1 @
1$
#3100000
0$
#3110000
b0 @
1$
#3120000
0$
#3130000
1!
b1 >
b1111111111 ?
b111 @
1$
#3140000
0$
#3150000
b110 @
1$
#3160000
0$
#3170000
b101 @
1$
#3180000
0$
#3190000
b100 @
1$
#3200000
0$
#3210000
b11 @
b1 (
b1000 )
1$
#3220000
0$
#3230000
b10 @
1$
#3240000
0$
#3250000
b1 @
1$
#3260000
0$
#3270000
b0 @
1$
#3280000
0$
#3290000
1+
b0 >
b111 @
1$
#3300000
0$
#3310000
1$
#3320000
0$
#3330000
1$
#3340000
0$
#3350000
1$
#3360000
0$
#3370000
0'
b1011010 B
b0 %
b1011010 A
1$
#3380000
0$
#3390000
b10 :
1$
#3400000
0$
#3410000
b0 :
1$
#3420000
0$
#3430000
b1 9
b11 ;
1$
#3440000
0$
#3450000
b10 ;
1$
#3460000
0$
#3470000
b1 ;
1$
#3480000
0$
#3490000
b0 ;
1$
#3500000
0$
#3510000
b10 9
b0 6
b111 ;
1$
#3520000
0$
#3530000
b110 ;
b0 )
1$
#3540000
0$
#3550000
b101 ;
1$
#3560000
0$
#3570000
b100 ;
1$
#3580000
0$
#3590000
b11 ;
1$
#3600000
0$
#3610000
b10 ;
1$
#3620000
0$
#3630000
b1 ;
1$
#3640000
0$
#3650000
b0 ;
1$
#3660000
0$
#3670000
b1 6
b111 ;
b1000000 8
1$
#3680000
0$
#3690000
b110 ;
1'
b1 )
1$
#3700000
0$
#3710000
b101 ;
b1 :
1$
#3720000
0$
#3730000
b100 ;
b11 :
1$
#3740000
0$
#3750000
b11 ;
1$
#3760000
0$
#3770000
b10 ;
1$
#3780000
0$
#3790000
b1 ;
1$
#3800000
0$
#3810000
b0 ;
1$
#3820000
0$
#3830000
b10 6
b111 ;
b1000010 8
1$
#3840000
0$
#3850000
b110 ;
0'
b10 )
1$
#3860000
0$
#3870000
b101 ;
b10 :
1$
#3880000
0$
#3890000
b100 ;
b0 :
1$
#3900000
0$
#3910000
b11 ;
1$
#3920000
0$
#3930000
b10 ;
1$
#3940000
0$
#3950000
b1 ;
1$
#3960000
0$
#3970000
b0 ;
1$
#3980000
0$
#3990000
b11 6
b111 ;
1$
#4000000
0$
#4010000
b110 ;
1'
b11 )
1$
#4020000
0$
#4030000
b101 ;
b1 :
1$
#4040000
0$
#4050000
b100 ;
b11 :
1$
#4060000
0$
#4070000
b11 ;
1$
#4080000
0$
#4090000
b10 ;
1$
#4100000
0$
#4110000
b1 ;
1$
#4120000
0$
#4130000
b0 ;
1$
#4140000
0$
#4150000
b100 6
b111 ;
b1001010 8
1$
#4160000
0$
#4170000
b110 ;
b100 )
1$
#4180000
0$
#4190000
b101 ;
1$
#4200000
0$
#4210000
b100 ;
1$
#4220000
0$
#4230000
b11 ;
1$
#4240000
0$
#4250000
b10 ;
1$
#4260000
0$
#4270000
b1 ;
1$
#4280000
0$
#4290000
b0 ;
1$
#4300000
0$
#4310000
b101 6
b111 ;
b1011010 8
1$
#4320000
0$
#4330000
b110 ;
0'
b101 )
1$
#4340000
0$
#4350000
b101 ;
b10 :
1$
#4360000
0$
#4370000
b100 ;
b0 :
1$
#4380000
0$
#4390000
b11 ;
1$
#4400000
0$
#4410000
b10 ;
1$
#4420000
0$
#4430000
b1 ;
1$
#4440000
0$
#4450000
b0 ;
1$
#4460000
0$
#4470000
b110 6
b111 ;
1$
#4480000
0$
#4490000
b110 ;
1'
b110 )
1$
#4500000
0$
#4510000
b101 ;
b1 :
1$
#4520000
0$
#4530000
b100 ;
b11 :
1$
#4540000
0$
#4550000
b11 ;
1$
#4560000
0$
#4570000
b10 ;
1$
#4580000
0$
#4590000
b1 ;
1$
#4600000
0$
#4610000
b0 ;
1$
#4620000
0$
#4630000
b111 6
b111 ;
1$
#4640000
0$
#4650000
b110 ;
0'
b111 )
1$
#4660000
0$
#4670000
b101 ;
b10 :
1$
#4680000
0$
#4690000
b100 ;
b0 :
1$
#4700000
0$
#4710000
b11 ;
1$
#4720000
0$
#4730000
b10 ;
1$
#4740000
0$
#4750000
b1 ;
1$
#4760000
0$
#4770000
b0 ;
1$
#4780000
0$
#4790000
b11 9
b111 ;
1$
#4800000
0$
#4810000
b110 ;
1'
b1000 )
1$
#4820000
0$
#4830000
b101 ;
b1 :
1$
#4840000
0$
#4850000
b100 ;
b11 :
1$
#4860000
0$
#4870000
b11 ;
1$
#4880000
0$
#4890000
b10 ;
1$
#4900000
0$
#4910000
b1 ;
1$
#4920000
0$
#4930000
b0 ;
1$
#4940000
0$
#4950000
b0 9
1,
b1011010 .
b1011010 7
1$
#4960000
0$
#4970000
0,
14
b1011010 3
b1011010 <
b1011010 "
b1011010 *
b1011010 2
1$
#4980000
0$
#4990000
0!
0+
b1010 >
b1010110100 ?
04
1$
#5000000
0$
#5010000
b110 @
1$
#5020000
0$
#5030000
b101 @
1$
#5040000
0$
#5050000
b100 @
1$
#5060000
0$
#5070000
b11 @
1$
#5080000
0$
#5090000
b10 @
1$
#5100000
0$
#5110000
b1 @
1$
#5120000
0$
#5130000
b0 @
1$
#5140000
0$
#5150000
b1001 >
b1101011010 ?
b111 @
1$
#5160000
0$
#5170000
b110 @
1$
#5180000
0$
#5190000
b101 @
1$
#5200000
0$
#5210000
b100 @
1$
#5220000
0$
#5230000
b11 @
b0 )
1$
#5240000
0$
#5250000
b10 @
1$
#5260000
0$
#5270000
b1 @
1$
#5280000
0$
#5290000
b0 @
1$
#5300000
0$
#5310000
1!
b1000 >
b1110101101 ?
b111 @
1$
#5320000
0$
#5330000
b110 @
1$
#5340000
0$
#5350000
b101 @
1$
#5360000
0$
#5370000
b100 @
1$
#5380000
0$
#5390000
b11 @
b10 %
b1 )
1$
#5400000
0$
#5410000
b10 @
1$
#5420000
0$
#5430000
b1 @
1$
#5440000
0$
#5450000
b0 @
1$
#5460000
0$
#5470000
0!
b111 >
b1111010110 ?
b111 @
1$
#5480000
0$
#5490000
b110 @
1$
#5500000
0$
#5510000
b101 @
1$
#5520000
0$
#5530000
b100 @
1$
#5540000
0$
#5550000
b11 @
b10 )
1$
#5560000
0$
#5570000
b10 @
1$
#5580000
0$
#5590000
b1 @
1$
#5600000
0$
#5610000
b0 @
1$
#5620000
0$
#5630000
1!
b110 >
b1111101011 ?
b111 @
1$
#5640000
0$
#5650000
b110 @
1$
#5660000
0$
#5670000
b101 @
1$
#5680000
0$
#5690000
b100 @
1$
#5700000
0$
#5710000
b11 @
b1010 %
b11 )
1$
#5720000
0$
#5730000
b10 @
1$
#5740000
0$
#5750000
b1 @
1$
#5760000
0$
#5770000
b0 @
1$
#5780000
0$
#5790000
b101 >
b1111110101 ?
b111 @
1$
#5800000
0$
#5810000
b110 @
1$
#5820000
0$
#5830000
b101 @
1$
#5840000
0$
#5850000
b100 @
1$
#5860000
0$
#5870000
b11 @
b11010 %
b100 )
1$
#5880000
0$
#5890000
b10 @
1$
#5900000
0$
#5910000
b1 @
1$
#5920000
0$
#5930000
b0 @
1$
#5940000
0$
#5950000
0!
b100 >
b1111111010 ?
b111 @
1$
#5960000
0$
#5970000
b110 @
1$
#5980000
0$
#5990000
b101 @
1$
#6000000
0$
#6010000
b100 @
1$
#6020000
0$
#6030000
b11 @
b101 )
1$
#6040000
0$
#6050000
b10 @
1$
#6060000
0$
#6070000
b1 @
1$
#6080000
0$
#6090000
b0 @
1$
#6100000
0$
#6110000
1!
b11 >
b1111111101 ?
b111 @
1$
#6120000
0$
#6130000
b110 @
1$
#6140000
0$
#6150000
b101 @
1$
#6160000
0$
#6170000
b100 @
1$
#6180000
0$
#6190000
b11 @
b1011010 %
b110 )
1$
#6200000
0$
#6210000
b10 @
1$
#6220000
0$
#6230000
b1 @
1$
#6240000
0$
#6250000
b0 @
1$
#6260000
0$
#6270000
0!
b10 >
b1111111110 ?
b111 @
1$
#6280000
0$
#6290000
b110 @
1$
#6300000
0$
#6310000
b101 @
1$
#6320000
0$
#6330000
b100 @
1$
#6340000
0$
#6350000
b11 @
b111 )
1$
#6360000
0$
#6370000
b10 @
1$
#6380000
0$
#6390000
b1 @
1$
#6400000
0$
#6410000
b0 @
1$
#6420000
0$
#6430000
1!
b1 >
b1111111111 ?
b111 @
1$
#6440000
0$
#6450000
b110 @
1$
#6460000
0$
#6470000
b101 @
1$
#6480000
0$
#6490000
b100 @
1$
#6500000
0$
#6510000
b11 @
b10 (
b1000 )
1$
#6520000
0$
#6530000
b10 @
1$
#6540000
0$
#6550000
b1 @
1$
#6560000
0$
#6570000
b0 @
1$
#6580000
0$
#6590000
1+
b0 >
b111 @
1$
#6600000
0$
#6610000
1$
#6620000
0$
#6630000
1$
#6640000
0$
#6650000
1$
#6660000
0$
#6670000
0'
b1010 B
b0 %
b1010 A
1$
#6680000
0$
#6690000
b10 :
1$
#6700000
0$
#6710000
b0 :
1$
#6720000
0$
#6730000
b1 9
b11 ;
1$
#6740000
0$
#6750000
b10 ;
1$
#6760000
0$
#6770000
b1 ;
1$
#6780000
0$
#6790000
b0 ;
1$
#6800000
0$
#6810000
b10 9
b0 6
b111 ;
1$
#6820000
0$
#6830000
b110 ;
b0 )
1$
#6840000
0$
#6850000
b101 ;
1$
#6860000
0$
#6870000
b100 ;
1$
#6880000
0$
#6890000
b11 ;
1$
#6900000
0$
#6910000
b10 ;
1$
#6920000
0$
#6930000
b1 ;
1$
#6940000
0$
#6950000
b0 ;
1$
#6960000
0$
#6970000
b1 6
b111 ;
1$
#6980000
0$
#6990000
b110 ;
1'
b1 )
1$
#7000000
0$
#7010000
b101 ;
b1 :
1$
#7020000
0$
#7030000
b100 ;
b11 :
1$
#7040000
0$
#7050000
b11 ;
1$
#7060000
0$
#7070000
b10 ;
1$
#7080000
0$
#7090000
b1 ;
1$
#7100000
0$
#7110000
b0 ;
1$
#7120000
0$
#7130000
b10 6
b111 ;
1$
#7140000
0$
#7150000
b110 ;
0'
b10 )
1$
#7160000
0$
#7170000
b101 ;
b10 :
1$
#7180000
0$
#7190000
b100 ;
b0 :
1$
#7200000
0$
#7210000
b11 ;
1$
#7220000
0$
#7230000
b10 ;
1$
#7240000
0$
#7250000
b1 ;
1$
#7260000
0$
#7270000
b0 ;
1$
#7280000
0$
#7290000
b11 6
b111 ;
1$
#7300000
0$
#7310000
b110 ;
1'
b11 )
1$
#7320000
0$
#7330000
b101 ;
b1 :
1$
#7340000
0$
#7350000
b100 ;
b11 :
1$
#7360000
0$
#7370000
b11 ;
1$
#7380000
0$
#7390000
b10 ;
1$
#7400000
0$
#7410000
b1 ;
1$
#7420000
0$
#7430000
b0 ;
1$
#7440000
0$
#7450000
b100 6
b111 ;
1$
#7460000
0$
#7470000
b110 ;
0'
b100 )
1$
#7480000
0$
#7490000
b101 ;
b10 :
1$
#7500000
0$
#7510000
b100 ;
b0 :
1$
#7520000
0$
#7530000
b11 ;
1$
#7540000
0$
#7550000
b10 ;
1$
#7560000
0$
#7570000
b1 ;
1$
#7580000
0$
#7590000
b0 ;
1$
#7600000
0$
#7610000
b101 6
b111 ;
b1001010 8
1$
#7620000
0$
#7630000
b110 ;
b101 )
1$
#7640000
0$
#7650000
b101 ;
1$
#7660000
0$
#7670000
b100 ;
1$
#7680000
0$
#7690000
b11 ;
1$
#7700000
0$
#7710000
b10 ;
1$
#7720000
0$
#7730000
b1 ;
1$
#7740000
0$
#7750000
b0 ;
1$
#7760000
0$
#7770000
b110 6
b111 ;
1$
#7780000
0$
#7790000
b110 ;
b110 )
1$
#7800000
0$
#7810000
b101 ;
1$
#7820000
0$
#7830000
b100 ;
1$
#7840000
0$
#7850000
b11 ;
1$
#7860000
0$
#7870000
b10 ;
1$
#7880000
0$
#7890000
b1 ;
1$
#7900000
0$
#7910000
b0 ;
1$
#7920000
0$
#7930000
b111 6
b111 ;
b1010 8
1$
#7940000
0$
#7950000
b110 ;
b111 )
1$
#7960000
0$
#7970000
b101 ;
1$
#7980000
0$
#7990000
b100 ;
1$
#8000000
0$
#8010000
b11 ;
1$
#8020000
0$
#8030000
b10 ;
1$
#8040000
0$
#8050000
b1 ;
1$
#8060000
0$
#8070000
b0 ;
1$
#8080000
0$
#8090000
b11 9
b111 ;
1$
#8100000
0$
#8110000
b110 ;
1'
b1000 )
1$
#8120000
0$
#8130000
b101 ;
b1 :
1$
#8140000
0$
#8150000
b100 ;
b11 :
1$
#8160000
0$
#8170000
b11 ;
1$
#8180000
0$
#8190000
b10 ;
1$
#8200000
0$
#8210000
b1 ;
1$
#8220000
0$
#8230000
b0 ;
1$
#8240000
0$
#8250000
b0 9
1,
b1010 .
b1010 7
1$
#8260000
0$
#8270000
0,
14
b1010 3
b1010 <
b1010 "
b1010 *
b1010 2
1$
#8280000
0$
#8290000
0!
0+
b1010 >
b1000010100 ?
04
1$
#8300000
0$
#8310000
b110 @
1$
#8320000
0$
#8330000
b101 @
1$
#8340000
0$
#8350000
b100 @
1$
#8360000
0$
#8370000
b11 @
1$
#8380000
0$
#8390000
b10 @
1$
#8400000
0$
#8410000
b1 @
1$
#8420000
0$
#8430000
b0 @
1$
#8440000
0$
#8450000
b1001 >
b1100001010 ?
b111 @
1$
#8460000
0$
#8470000
b110 @
1$
#8480000
0$
#8490000
b101 @
1$
#8500000
0$
#8510000
b100 @
1$
#8520000
0$
#8530000
b11 @
b0 )
1$
#8540000
0$
#8550000
b10 @
1$
#8560000
0$
#8570000
b1 @
1$
#8580000
0$
#8590000
b0 @
1$
#8600000
0$
#8610000
1!
b1000 >
b1110000101 ?
b111 @
1$
#8620000
0$
#8630000
b110 @
1$
#8640000
0$
#8650000
b101 @
1$
#8660000
0$
#8670000
b100 @
1$
#8680000
0$
#8690000
b11 @
b10 %
b1 )
1$
#8700000
0$
#8710000
b10 @
1$
#8720000
0$
#8730000
b1 @
1$
#8740000
0$
#8750000
b0 @
1$
#8760000
0$
#8770000
0!
b111 >
b1111000010 ?
b111 @
1$
#8780000
0$
#8790000
b110 @
1$
#8800000
0$
#8810000
b101 @
1$
#8820000
0$
#8830000
b100 @
1$
#8840000
0$
#8850000
b11 @
b10 )
1$
#8860000
0$
#8870000
b10 @
1$
#8880000
0$
#8890000
b1 @
1$
#8900000
0$
#8910000
b0 @
1$
#8920000
0$
#8930000
1!
b110 >
b1111100001 ?
b111 @
1$
#8940000
0$
#8950000
b110 @
1$
#8960000
0$
#8970000
b101 @
1$
#8980000
0$
#8990000
b100 @
1$
#9000000
0$
#9010000
b11 @
b1010 %
b11 )
1$
#9020000
0$
#9030000
b10 @
1$
#9040000
0$
#9050000
b1 @
1$
#9060000
0$
#9070000
b0 @
1$
#9080000
0$
#9090000
0!
b101 >
b1111110000 ?
b111 @
1$
#9100000
0$
#9110000
b110 @
1$
#9120000
0$
#9130000
b101 @
1$
#9140000
0$
#9150000
b100 @
1$
#9160000
0$
#9170000
b11 @
b100 )
1$
#9180000
0$
#9190000
b10 @
1$
#9200000
0$
#9210000
b1 @
1$
#9220000
0$
#9230000
b0 @
1$
#9240000
0$
#9250000
b100 >
b1111111000 ?
b111 @
1$
#9260000
0$
#9270000
b110 @
1$
#9280000
0$
#9290000
b101 @
1$
#9300000
0$
#9310000
b100 @
1$
#9320000
0$
